alliance_platform/base_settings.py
alliance_platform/core/__init__.py
alliance_platform/core/auth.py
alliance_platform/core/display.py
alliance_platform/core/settings.py
alliance_platform/core/util.py
alliance_platform/py.typed
alliance_platform_core-0.0.5.dist-info/METADATA
alliance_platform_core-0.0.5.dist-info/WHEEL
alliance_platform_core-0.0.5.dist-info/entry_points.txt
alliance_platform_core-0.0.5.dist-info/RECORD
