Metadata-Version: 2.1
Name: alliance-platform-core
Version: 0.0.5
Summary: Alliance Platform Core
Author-Email: Alliance Software <support@alliancesoftware.com.au>
License: BSD-2-Clause
Requires-Python: >=3.11
